{
  "PIIOHCJFHBD": [
    {
      "BBPHAPFBFHK": 1,
      "IIBAJDOLFBM": [
        {
          "BNFLNMGOJCM": 1,
          "BPODDGNIDBG": [
            "1",
            "1"
          ]
        },
        {
          "BNFLNMGOJCM": 1,
          "BPODDGNIDBG": [
            "3",
            "1"
          ]
        },
        {
          "BNFLNMGOJCM": 1,
          "BPODDGNIDBG": [
            "11",
            "1"
          ]
        },
        {
          "BNFLNMGOJCM": 2,
          "BPODDGNIDBG": [
            "1"
          ]
        },
        {
          "BNFLNMGOJCM": 5,
          "BPODDGNIDBG": [
            "3"
          ]
        },
        {
          "BNFLNMGOJCM": 3,
          "BPODDGNIDBG": [
            "8"
          ]
        }
      ],
      "GELNDPJNLJM": 0,
      "IAHNDJDBCAJ": ""
    },
    {
      "BBPHAPFBFHK": 2,
      "IIBAJDOLFBM": [
        {
          "BNFLNMGOJCM": 40,
          "BPODDGNIDBG": [
            "8"
          ]
        },
        {
          "BNFLNMGOJCM": 20,
          "BPODDGNIDBG": [
            "1"
          ]
        },
        {
          "BNFLNMGOJCM": 25,
          "BPODDGNIDBG": [
            "400"
          ]
        },
        {
          "BNFLNMGOJCM": 10,
          "BPODDGNIDBG": [
            "1",
            "1",
            "1",
            "1"
          ]
        },
        {
          "BNFLNMGOJCM": 10,
          "BPODDGNIDBG": [
            "3",
            "2",
            "1",
            "1"
          ]
        },
        {
          "BNFLNMGOJCM": 10,
          "BPODDGNIDBG": [
            "11",
            "0",
            "1",
            "1"
          ]
        },
        {
          "BNFLNMGOJCM": 76,
          "BPODDGNIDBG": [
            "200"
          ]
        },
        {
          "BNFLNMGOJCM": 23,
          "BPODDGNIDBG": [

          ]
        },
        {
          "BNFLNMGOJCM": 6,
          "BPODDGNIDBG": [
            "2"
          ]
        }
      ],
      "GELNDPJNLJM": 0,
      "IAHNDJDBCAJ": ""
    },
    {
      "BBPHAPFBFHK": 3,
      "IIBAJDOLFBM": [
        {
          "BNFLNMGOJCM": 47,
          "BPODDGNIDBG": [
            "3",
            "24"
          ]
        }
      ],
      "GELNDPJNLJM": 3,
      "IAHNDJDBCAJ": "\u304A\u5F85\u305F\u305B\u3001\u3053\u308C\u3067\u51FA\u6483\u524D\u306E\u6E96\u5099\u306F\u5B8C\u4E86\u3088"
    },
    {
      "BBPHAPFBFHK": 4,
      "IIBAJDOLFBM": [
        {
          "BNFLNMGOJCM": 47,
          "BPODDGNIDBG": [
            "11",
            "25"
          ]
        }
      ],
      "GELNDPJNLJM": 11,
      "IAHNDJDBCAJ": "\u305D\u308C\u3058\u3083\u3001\u30D5\u30EC\u30A4\u30A2\u3002\n\u3044\u3044\u611F\u3058\u306E\u3084\u3064\u3092\u983C\u3080"
    },
    {
      "BBPHAPFBFHK": 5,
      "IIBAJDOLFBM": [
        {
          "BNFLNMGOJCM": 30,
          "BPODDGNIDBG": [
            "1",
            "2"
          ]
        },
        {
          "BNFLNMGOJCM": 47,
          "BPODDGNIDBG": [
            "1",
            "26"
          ]
        }
      ],
      "GELNDPJNLJM": 1,
      "IAHNDJDBCAJ": "\u4EFB\u305B\u3066\u3001\u30CF\u30E4\u30C6\uFF01"
    },
    {
      "BBPHAPFBFHK": 6,
      "IIBAJDOLFBM": [
        {
          "BNFLNMGOJCM": 47,
          "BPODDGNIDBG": [
            "1",
            "27"
          ]
        }
      ],
      "GELNDPJNLJM": 1,
      "IAHNDJDBCAJ": "\u3069\u3093\u306A\u6575\u304C\u51FA\u3066\u304D\u3066\u3082\u3001\n\u79C1\u304C\u6B4C\u3067\u3054\u308A\u3054\u308A\u5FDC\u63F4\u3059\u308B\u304B\u3093\u306D\uFF01"
    },
    {
      "BBPHAPFBFHK": 7,
      "IIBAJDOLFBM": [
        {
          "BNFLNMGOJCM": 47,
          "BPODDGNIDBG": [
            "11",
            "28"
          ]
        }
      ],
      "GELNDPJNLJM": 11,
      "IAHNDJDBCAJ": "\u3042\u3042\u3001\u4E00\u6C17\u306B\u7247\u4ED8\u3051\u308B\u305E\uFF01"
    },
    {
      "BBPHAPFBFHK": 8,
      "IIBAJDOLFBM": [
        {
          "BNFLNMGOJCM": 47,
          "BPODDGNIDBG": [
            "3",
            "29"
          ]
        }
      ],
      "GELNDPJNLJM": 3,
      "IAHNDJDBCAJ": "2\u4EBA\u3068\u3082\u3001\u305D\u308C\u3058\u3083\u884C\u304F\u308F\u3088\uFF01"
    },
    {
      "BBPHAPFBFHK": 9,
      "IIBAJDOLFBM": [
        {
          "BNFLNMGOJCM": 45,
          "BPODDGNIDBG": [
            "400"
          ]
        },
        {
          "BNFLNMGOJCM": 26,
          "BPODDGNIDBG": [
            "400"
          ]
        },
        {
          "BNFLNMGOJCM": 46,
          "BPODDGNIDBG": [

          ]
        }
      ],
      "GELNDPJNLJM": 0,
      "IAHNDJDBCAJ": ""
    },
    {
      "BBPHAPFBFHK": 10,
      "IIBAJDOLFBM": [
        {
          "BNFLNMGOJCM": 72,
          "BPODDGNIDBG": [
            "-1",
            "4"
          ]
        }
      ],
      "GELNDPJNLJM": 0,
      "IAHNDJDBCAJ": ""
    }
  ]
}
