{
  "PIIOHCJFHBD": [
    {
      "BBPHAPFBFHK": 1,
      "IIBAJDOLFBM": [
        {
          "BNFLNMGOJCM": 2,
          "BPODDGNIDBG": [
            "20\r"
          ]
        },
        {
          "BNFLNMGOJCM": 2,
          "BPODDGNIDBG": [
            "44"
          ]
        },
        {
          "BNFLNMGOJCM": 1,
          "BPODDGNIDBG": [
            "5",
            "1\r"
          ]
        },
        {
          "BNFLNMGOJCM": 1,
          "BPODDGNIDBG": [
            "4",
            "1\r"
          ]
        },
        {
          "BNFLNMGOJCM": 1,
          "BPODDGNIDBG": [
            "1",
            "1\r"
          ]
        },
        {
          "BNFLNMGOJCM": 1,
          "BPODDGNIDBG": [
            "3",
            "1"
          ]
        },
        {
          "BNFLNMGOJCM": 9,
          "BPODDGNIDBG": [
            "8",
            "2"
          ]
        },
        {
          "BNFLNMGOJCM": 45,
          "BPODDGNIDBG": [
            "400"
          ]
        },
        {
          "BNFLNMGOJCM": 46,
          "BPODDGNIDBG": [

          ]
        },
        {
          "BNFLNMGOJCM": 3,
          "BPODDGNIDBG": [
            "13"
          ]
        },
        {
          "BNFLNMGOJCM": 5,
          "BPODDGNIDBG": [
            "302201"
          ]
        },
        {
          "BNFLNMGOJCM": 90,
          "BPODDGNIDBG": [
            "302201"
          ]
        }
      ],
      "GELNDPJNLJM": 0,
      "IAHNDJDBCAJ": ""
    },
    {
      "BBPHAPFBFHK": 2,
      "IIBAJDOLFBM": [
        {
          "BNFLNMGOJCM": 20,
          "BPODDGNIDBG": [
            "20"
          ]
        },
        {
          "BNFLNMGOJCM": 76,
          "BPODDGNIDBG": [
            "200"
          ]
        },
        {
          "BNFLNMGOJCM": 77,
          "BPODDGNIDBG": [
            "0"
          ]
        }
      ],
      "GELNDPJNLJM": 0,
      "IAHNDJDBCAJ": ""
    },
    {
      "BBPHAPFBFHK": 3,
      "IIBAJDOLFBM": [
        {
          "BNFLNMGOJCM": 94,
          "BPODDGNIDBG": [
            "302201",
            "1"
          ]
        },
        {
          "BNFLNMGOJCM": 25,
          "BPODDGNIDBG": [
            "1200"
          ]
        },
        {
          "BNFLNMGOJCM": 91,
          "BPODDGNIDBG": [
            "302201",
            "0",
            "cut_01"
          ]
        },
        {
          "BNFLNMGOJCM": 92,
          "BPODDGNIDBG": [
            "302201"
          ]
        }
      ],
      "GELNDPJNLJM": 0,
      "IAHNDJDBCAJ": ""
    },
    {
      "BBPHAPFBFHK": 4,
      "IIBAJDOLFBM": [
        {
          "BNFLNMGOJCM": 91,
          "BPODDGNIDBG": [
            "302201",
            "0",
            "cut_02"
          ]
        },
        {
          "BNFLNMGOJCM": 42,
          "BPODDGNIDBG": [
            "16"
          ]
        },
        {
          "BNFLNMGOJCM": 92,
          "BPODDGNIDBG": [
            "302201"
          ]
        }
      ],
      "GELNDPJNLJM": 0,
      "IAHNDJDBCAJ": ""
    },
    {
      "BBPHAPFBFHK": 5,
      "IIBAJDOLFBM": [
        {
          "BNFLNMGOJCM": 91,
          "BPODDGNIDBG": [
            "302201",
            "0",
            "cut_03"
          ]
        },
        {
          "BNFLNMGOJCM": 92,
          "BPODDGNIDBG": [
            "302201"
          ]
        }
      ],
      "GELNDPJNLJM": 0,
      "IAHNDJDBCAJ": ""
    },
    {
      "BBPHAPFBFHK": 6,
      "IIBAJDOLFBM": [
        {
          "BNFLNMGOJCM": 42,
          "BPODDGNIDBG": [
            "19"
          ]
        },
        {
          "BNFLNMGOJCM": 91,
          "BPODDGNIDBG": [
            "302201",
            "0",
            "cut_04"
          ]
        },
        {
          "BNFLNMGOJCM": 44,
          "BPODDGNIDBG": [
            "5",
            "0231"
          ]
        },
        {
          "BNFLNMGOJCM": 92,
          "BPODDGNIDBG": [
            "302201"
          ]
        }
      ],
      "GELNDPJNLJM": 0,
      "IAHNDJDBCAJ": ""
    },
    {
      "BBPHAPFBFHK": 7,
      "IIBAJDOLFBM": [
        {
          "BNFLNMGOJCM": 91,
          "BPODDGNIDBG": [
            "302201",
            "0",
            "cut_05"
          ]
        },
        {
          "BNFLNMGOJCM": 92,
          "BPODDGNIDBG": [
            "302201"
          ]
        }
      ],
      "GELNDPJNLJM": 0,
      "IAHNDJDBCAJ": ""
    },
    {
      "BBPHAPFBFHK": 8,
      "IIBAJDOLFBM": [
        {
          "BNFLNMGOJCM": 40,
          "BPODDGNIDBG": [
            "13"
          ]
        },
        {
          "BNFLNMGOJCM": 25,
          "BPODDGNIDBG": [
            "1200"
          ]
        },
        {
          "BNFLNMGOJCM": 77,
          "BPODDGNIDBG": [
            "1"
          ]
        },
        {
          "BNFLNMGOJCM": 23,
          "BPODDGNIDBG": [

          ]
        }
      ],
      "GELNDPJNLJM": 0,
      "IAHNDJDBCAJ": ""
    },
    {
      "BBPHAPFBFHK": 9,
      "IIBAJDOLFBM": [
        {
          "BNFLNMGOJCM": 10,
          "BPODDGNIDBG": [
            "4",
            "1",
            "1",
            "1"
          ]
        },
        {
          "BNFLNMGOJCM": 10,
          "BPODDGNIDBG": [
            "5",
            "0",
            "1",
            "1"
          ]
        },
        {
          "BNFLNMGOJCM": 10,
          "BPODDGNIDBG": [
            "1",
            "2",
            "1",
            "1"
          ]
        }
      ],
      "GELNDPJNLJM": 0,
      "IAHNDJDBCAJ": ""
    },
    {
      "BBPHAPFBFHK": 10,
      "IIBAJDOLFBM": [
        {
          "BNFLNMGOJCM": 30,
          "BPODDGNIDBG": [
            "4",
            "4"
          ]
        }
      ],
      "GELNDPJNLJM": 4,
      "IAHNDJDBCAJ": "\u2026\u2026"
    },
    {
      "BBPHAPFBFHK": 11,
      "IIBAJDOLFBM": [
        {
          "BNFLNMGOJCM": 30,
          "BPODDGNIDBG": [
            "5",
            "1"
          ]
        }
      ],
      "GELNDPJNLJM": 5,
      "IAHNDJDBCAJ": "\u2026\u2026"
    },
    {
      "BBPHAPFBFHK": 12,
      "IIBAJDOLFBM": [
        {
          "BNFLNMGOJCM": 30,
          "BPODDGNIDBG": [
            "1",
            "1"
          ]
        },
        {
          "BNFLNMGOJCM": 44,
          "BPODDGNIDBG": [
            "1",
            "283"
          ]
        }
      ],
      "GELNDPJNLJM": 1,
      "IAHNDJDBCAJ": "\u3048\u3001\u3048\u30FC\u3068\u2026\u30DE\u30AD\u30CA\u3055\u3093\u3001\u30EC\u30A4\u30CA\u3055\u3093\u2026\uFF1F"
    },
    {
      "BBPHAPFBFHK": 13,
      "IIBAJDOLFBM": [
        {
          "BNFLNMGOJCM": 44,
          "BPODDGNIDBG": [
            "4",
            "266"
          ]
        }
      ],
      "GELNDPJNLJM": 4,
      "IAHNDJDBCAJ": "\u30EC\u30A4\u30EC\u30A4\u306A\u3093\u3066\u3001\u3082\u3046\u77E5\u3089\u306A\u3044\uFF01"
    },
    {
      "BBPHAPFBFHK": 14,
      "IIBAJDOLFBM": [
        {
          "BNFLNMGOJCM": 44,
          "BPODDGNIDBG": [
            "5",
            "93"
          ]
        }
      ],
      "GELNDPJNLJM": 5,
      "IAHNDJDBCAJ": "\u305D\u308C\u306F\u3053\u3063\u3061\u306E\u53F0\u8A5E"
    },
    {
      "BBPHAPFBFHK": 15,
      "IIBAJDOLFBM": [
        {
          "BNFLNMGOJCM": 30,
          "BPODDGNIDBG": [
            "1",
            "4\r"
          ]
        }
      ],
      "GELNDPJNLJM": 1,
      "IAHNDJDBCAJ": "\u3075\u3047\uFF01\uFF1F"
    },
    {
      "BBPHAPFBFHK": 16,
      "IIBAJDOLFBM": [
        {
          "BNFLNMGOJCM": 44,
          "BPODDGNIDBG": [
            "1",
            "287"
          ]
        }
      ],
      "GELNDPJNLJM": 1,
      "IAHNDJDBCAJ": "\u3053\u308C\u306F\u56F0\u3063\u305F\u3053\u3068\u306B\u306A\u3063\u305F\u3093\u3088\u2026"
    },
    {
      "BBPHAPFBFHK": 17,
      "IIBAJDOLFBM": [
        {
          "BNFLNMGOJCM": 26,
          "BPODDGNIDBG": [
            "1000"
          ]
        },
        {
          "BNFLNMGOJCM": 76,
          "BPODDGNIDBG": [
            "400"
          ]
        },
        {
          "BNFLNMGOJCM": 24,
          "BPODDGNIDBG": [

          ]
        },
        {
          "BNFLNMGOJCM": 11,
          "BPODDGNIDBG": [
            "4"
          ]
        },
        {
          "BNFLNMGOJCM": 12,
          "BPODDGNIDBG": [
            "4"
          ]
        },
        {
          "BNFLNMGOJCM": 11,
          "BPODDGNIDBG": [
            "5"
          ]
        },
        {
          "BNFLNMGOJCM": 12,
          "BPODDGNIDBG": [
            "5"
          ]
        },
        {
          "BNFLNMGOJCM": 11,
          "BPODDGNIDBG": [
            "1"
          ]
        },
        {
          "BNFLNMGOJCM": 12,
          "BPODDGNIDBG": [
            "1"
          ]
        },
        {
          "BNFLNMGOJCM": 40,
          "BPODDGNIDBG": [
            "13"
          ]
        },
        {
          "BNFLNMGOJCM": 10,
          "BPODDGNIDBG": [
            "1",
            "2",
            "1",
            "1"
          ]
        },
        {
          "BNFLNMGOJCM": 10,
          "BPODDGNIDBG": [
            "3",
            "1",
            "1",
            "1"
          ]
        },
        {
          "BNFLNMGOJCM": 20,
          "BPODDGNIDBG": [
            "44"
          ]
        }
      ],
      "GELNDPJNLJM": 0,
      "IAHNDJDBCAJ": ""
    },
    {
      "BBPHAPFBFHK": 18,
      "IIBAJDOLFBM": [

      ],
      "GELNDPJNLJM": 1,
      "IAHNDJDBCAJ": ""
    },
    {
      "BBPHAPFBFHK": 19,
      "IIBAJDOLFBM": [
        {
          "BNFLNMGOJCM": 25,
          "BPODDGNIDBG": [
            "600"
          ]
        },
        {
          "BNFLNMGOJCM": 76,
          "BPODDGNIDBG": [
            "200"
          ]
        },
        {
          "BNFLNMGOJCM": 23,
          "BPODDGNIDBG": [

          ]
        }
      ],
      "GELNDPJNLJM": 0,
      "IAHNDJDBCAJ": ""
    },
    {
      "BBPHAPFBFHK": 20,
      "IIBAJDOLFBM": [
        {
          "BNFLNMGOJCM": 30,
          "BPODDGNIDBG": [
            "3",
            "1\r"
          ]
        },
        {
          "BNFLNMGOJCM": 44,
          "BPODDGNIDBG": [
            "3",
            "272"
          ]
        }
      ],
      "GELNDPJNLJM": 3,
      "IAHNDJDBCAJ": "\u3048\uFF1F\r\n\u30DE\u30AD\u30CA\u3068\u30EC\u30A4\u30CA\u304C\u55A7\u5629\u3092\u3057\u3066\u308B\uFF1F"
    },
    {
      "BBPHAPFBFHK": 21,
      "IIBAJDOLFBM": [
        {
          "BNFLNMGOJCM": 44,
          "BPODDGNIDBG": [
            "1",
            "257"
          ]
        },
        {
          "BNFLNMGOJCM": 30,
          "BPODDGNIDBG": [
            "1",
            "1"
          ]
        }
      ],
      "GELNDPJNLJM": 1,
      "IAHNDJDBCAJ": "\u307B\u3044\u306A\uFF01\r\n\u3076\u3063\u3061\u3083\u3074\u308A\u3074\u308A\u3057\u3066\u305F\u3093\u3088\u2026"
    },
    {
      "BBPHAPFBFHK": 22,
      "IIBAJDOLFBM": [
        {
          "BNFLNMGOJCM": 30,
          "BPODDGNIDBG": [
            "1",
            "4\r"
          ]
        }
      ],
      "GELNDPJNLJM": 1,
      "IAHNDJDBCAJ": "\u63A7\u3048\u5BA4\u306B\u6765\u305F\u3068\u304D\u304B\u3089\u305A\u3063\u3068\u305D\u3093\u306A\u611F\u3058\u3067\r\n\u304A\u4E92\u3044\u4E00\u8A00\u3082\u3057\u3083\u3079\u3063\u3066\u306A\u304F\u3066\u2026"
    },
    {
      "BBPHAPFBFHK": 23,
      "IIBAJDOLFBM": [
        {
          "BNFLNMGOJCM": 30,
          "BPODDGNIDBG": [
            "3",
            "2\r"
          ]
        },
        {
          "BNFLNMGOJCM": 44,
          "BPODDGNIDBG": [
            "3",
            "4"
          ]
        }
      ],
      "GELNDPJNLJM": 3,
      "IAHNDJDBCAJ": "\u2026\u3075\u3075\u3063\uFF01"
    },
    {
      "BBPHAPFBFHK": 24,
      "IIBAJDOLFBM": [

      ],
      "GELNDPJNLJM": 1,
      "IAHNDJDBCAJ": "\u30AB\u30CA\u30E1\u3055\u3093\uFF1F"
    },
    {
      "BBPHAPFBFHK": 25,
      "IIBAJDOLFBM": [
        {
          "BNFLNMGOJCM": 44,
          "BPODDGNIDBG": [
            "3",
            "93"
          ]
        }
      ],
      "GELNDPJNLJM": 3,
      "IAHNDJDBCAJ": "\u3054\u3081\u3093\u306A\u3055\u3044\uFF01\r\n\u306A\u3093\u3060\u304B\u3061\u3087\u3063\u3068\u61D0\u304B\u3057\u304F\u3066\u2026"
    },
    {
      "BBPHAPFBFHK": 26,
      "IIBAJDOLFBM": [
        {
          "BNFLNMGOJCM": 30,
          "BPODDGNIDBG": [
            "3",
            "1"
          ]
        }
      ],
      "GELNDPJNLJM": 3,
      "IAHNDJDBCAJ": "\u3042\u306E2\u4EBA\u3001\u6614\u306F\u3044\u3064\u3082\u55A7\u5629\u3070\u3063\u304B\u308A\u3057\u3066\u305F\u304B\u3089"
    },
    {
      "BBPHAPFBFHK": 27,
      "IIBAJDOLFBM": [
        {
          "BNFLNMGOJCM": 44,
          "BPODDGNIDBG": [
            "1",
            "283"
          ]
        }
      ],
      "GELNDPJNLJM": 1,
      "IAHNDJDBCAJ": "\u305D\u3046\u306A\u3093\u304B\u306D\uFF1F\r\n\u3067\u3082\u3001\u30E9\u30A4\u30D6\u3082\u3042\u308B\u3057\u3001\u65E9\u304F\u306A\u3093\u3068\u304B\u305B\u3093\u3068\u2026\uFF01"
    },
    {
      "BBPHAPFBFHK": 28,
      "IIBAJDOLFBM": [
        {
          "BNFLNMGOJCM": 30,
          "BPODDGNIDBG": [
            "3",
            "2\r"
          ]
        },
        {
          "BNFLNMGOJCM": 44,
          "BPODDGNIDBG": [
            "3",
            "290"
          ]
        }
      ],
      "GELNDPJNLJM": 3,
      "IAHNDJDBCAJ": "\u3046\u30FC\u3093\u3001\u305D\u3046\u306D\u2026\u3067\u3082\r\n\u3042\u306E2\u4EBA\u306E\u3053\u3068\u3060\u3057\u3001\u304D\u3063\u3068\u5927\u4E08\u592B\u3060\u3068\u601D\u3046\u308F\u3088"
    },
    {
      "BBPHAPFBFHK": 29,
      "IIBAJDOLFBM": [

      ],
      "GELNDPJNLJM": 1,
      "IAHNDJDBCAJ": "\u307B\u3001\u307B\u3063\u3068\u3044\u3066\u5927\u4E08\u592B\u306A\u3093\u304B\u306D\uFF01\uFF1F"
    },
    {
      "BBPHAPFBFHK": 30,
      "IIBAJDOLFBM": [
        {
          "BNFLNMGOJCM": 30,
          "BPODDGNIDBG": [
            "3",
            "5\r"
          ]
        },
        {
          "BNFLNMGOJCM": 44,
          "BPODDGNIDBG": [
            "3",
            "255"
          ]
        }
      ],
      "GELNDPJNLJM": 3,
      "IAHNDJDBCAJ": "\u3048\u3048\u3002\u3060\u304B\u3089\u307B\u3089\u3001\u30D5\u30EC\u30A4\u30A2\u3082\r\n\u305D\u308D\u305D\u308D\u30E9\u30A4\u30D6\u306E\u6E96\u5099\u3092\u3057\u3066\u306D"
    },
    {
      "BBPHAPFBFHK": 31,
      "IIBAJDOLFBM": [
        {
          "BNFLNMGOJCM": 11,
          "BPODDGNIDBG": [
            "3"
          ]
        },
        {
          "BNFLNMGOJCM": 12,
          "BPODDGNIDBG": [
            "3"
          ]
        }
      ],
      "GELNDPJNLJM": 0,
      "IAHNDJDBCAJ": ""
    },
    {
      "BBPHAPFBFHK": 32,
      "IIBAJDOLFBM": [
        {
          "BNFLNMGOJCM": 44,
          "BPODDGNIDBG": [
            "1",
            "282"
          ]
        }
      ],
      "GELNDPJNLJM": 1,
      "IAHNDJDBCAJ": "\u672C\u5F53\u306B\u5927\u4E08\u592B\u306A\u3093\u304B\u306D\u3047\u2026\uFF1F"
    },
    {
      "BBPHAPFBFHK": 33,
      "IIBAJDOLFBM": [
        {
          "BNFLNMGOJCM": 13,
          "BPODDGNIDBG": [
            "8",
            "1",
            "2",
            "1"
          ]
        },
        {
          "BNFLNMGOJCM": 42,
          "BPODDGNIDBG": [
            "21"
          ]
        },
        {
          "BNFLNMGOJCM": 76,
          "BPODDGNIDBG": [
            "400"
          ]
        }
      ],
      "GELNDPJNLJM": 0,
      "IAHNDJDBCAJ": ""
    },
    {
      "BBPHAPFBFHK": 34,
      "IIBAJDOLFBM": [
        {
          "BNFLNMGOJCM": 30,
          "BPODDGNIDBG": [
            "8",
            "1\r"
          ]
        },
        {
          "BNFLNMGOJCM": 44,
          "BPODDGNIDBG": [
            "8",
            "98"
          ]
        }
      ],
      "GELNDPJNLJM": 8,
      "IAHNDJDBCAJ": "\u306D\u3047\u3001\u30D5\u30EC\u30A4\u30A2\uFF01\r\n\u2026\u3063\u3066\u3001\u3069\u3046\u304B\u3057\u305F\u306E\uFF1F"
    },
    {
      "BBPHAPFBFHK": 35,
      "IIBAJDOLFBM": [
        {
          "BNFLNMGOJCM": 44,
          "BPODDGNIDBG": [
            "1",
            "107"
          ]
        },
        {
          "BNFLNMGOJCM": 30,
          "BPODDGNIDBG": [
            "1",
            "1"
          ]
        }
      ],
      "GELNDPJNLJM": 1,
      "IAHNDJDBCAJ": "\u30DF\u30EC\u30FC\u30CC\u3055\u3093\uFF01\r\n\u5B9F\u306F\u3001\u3061\u3087\u3063\u3068\u56F0\u3063\u305F\u3053\u3068\u304C\u3042\u3063\u305F\u3093\u3088"
    },
    {
      "BBPHAPFBFHK": 36,
      "IIBAJDOLFBM": [
        {
          "BNFLNMGOJCM": 26,
          "BPODDGNIDBG": [
            "1000"
          ]
        },
        {
          "BNFLNMGOJCM": 76,
          "BPODDGNIDBG": [
            "400"
          ]
        },
        {
          "BNFLNMGOJCM": 24,
          "BPODDGNIDBG": [

          ]
        }
      ],
      "GELNDPJNLJM": 0,
      "IAHNDJDBCAJ": ""
    },
    {
      "BBPHAPFBFHK": 37,
      "IIBAJDOLFBM": [
        {
          "BNFLNMGOJCM": 25,
          "BPODDGNIDBG": [
            "600"
          ]
        },
        {
          "BNFLNMGOJCM": 76,
          "BPODDGNIDBG": [
            "200"
          ]
        },
        {
          "BNFLNMGOJCM": 23,
          "BPODDGNIDBG": [

          ]
        }
      ],
      "GELNDPJNLJM": 0,
      "IAHNDJDBCAJ": ""
    },
    {
      "BBPHAPFBFHK": 38,
      "IIBAJDOLFBM": [
        {
          "BNFLNMGOJCM": 44,
          "BPODDGNIDBG": [
            "8",
            "261"
          ]
        }
      ],
      "GELNDPJNLJM": 8,
      "IAHNDJDBCAJ": "\u3075\u30FC\u3093\u3002\u30DE\u30AD\u30CA\u3068\u30EC\u30A4\u30CA\u304C\u55A7\u5629\u306D\u3047"
    },
    {
      "BBPHAPFBFHK": 39,
      "IIBAJDOLFBM": [
        {
          "BNFLNMGOJCM": 30,
          "BPODDGNIDBG": [
            "1",
            "1"
          ]
        }
      ],
      "GELNDPJNLJM": 1,
      "IAHNDJDBCAJ": "\u307B\u3044\u306A\u2026"
    },
    {
      "BBPHAPFBFHK": 40,
      "IIBAJDOLFBM": [
        {
          "BNFLNMGOJCM": 30,
          "BPODDGNIDBG": [
            "1",
            "4\r"
          ]
        },
        {
          "BNFLNMGOJCM": 44,
          "BPODDGNIDBG": [
            "1",
            "288"
          ]
        }
      ],
      "GELNDPJNLJM": 1,
      "IAHNDJDBCAJ": "\u79C1\u306F\u3044\u3064\u3082\u4EF2\u826F\u304F\u3057\u3066\u308B2\u4EBA\u3057\u304B\r\n\u898B\u305F\u3053\u3068\u306A\u3044\u304B\u3089\u3001\u5FC3\u914D\u306B\u306A\u3063\u3066\u304D\u3061\u3083\u3063\u305F\u3093\u3067\u3059"
    },
    {
      "BBPHAPFBFHK": 41,
      "IIBAJDOLFBM": [

      ],
      "GELNDPJNLJM": 1,
      "IAHNDJDBCAJ": "\u30AB\u30CA\u30E1\u3055\u3093\u306F\u5927\u4E08\u592B\u3063\u3066\u8A00\u3063\u3066\u305F\u3093\u3084\u3051\u3069\u2026"
    },
    {
      "BBPHAPFBFHK": 42,
      "IIBAJDOLFBM": [
        {
          "BNFLNMGOJCM": 30,
          "BPODDGNIDBG": [
            "8",
            "4\r"
          ]
        },
        {
          "BNFLNMGOJCM": 44,
          "BPODDGNIDBG": [
            "8",
            "8"
          ]
        }
      ],
      "GELNDPJNLJM": 8,
      "IAHNDJDBCAJ": "\u3046\u30FC\u3093\u3002\u3067\u3082\u3001\u30E9\u30A4\u30D6\u672C\u756A\u307E\u3067\u305D\u3093\u306A\u8ABF\u5B50\u3058\u3083\r\n\u30D5\u30EC\u30A4\u30A2\u304C\u4E0D\u5B89\u306B\u306A\u308B\u306E\u3082\u7121\u7406\u306A\u3044\u308F\u3088\u306D\u30FC"
    },
    {
      "BBPHAPFBFHK": 43,
      "IIBAJDOLFBM": [
        {
          "BNFLNMGOJCM": 30,
          "BPODDGNIDBG": [
            "8",
            "2\r"
          ]
        },
        {
          "BNFLNMGOJCM": 44,
          "BPODDGNIDBG": [
            "8",
            "270"
          ]
        }
      ],
      "GELNDPJNLJM": 8,
      "IAHNDJDBCAJ": "\u2026\u3088\u3057\u3063\uFF01\u30D5\u30EC\u30A4\u30A2\u306E\u305F\u3081\u306B\r\n\u3042\u305F\u3057\u304C\u4E00\u808C\u8131\u3044\u3067\u3042\u3052\u308B\u308F\uFF01"
    },
    {
      "BBPHAPFBFHK": 44,
      "IIBAJDOLFBM": [
        {
          "BNFLNMGOJCM": 30,
          "BPODDGNIDBG": [
            "1",
            "1\r"
          ]
        },
        {
          "BNFLNMGOJCM": 44,
          "BPODDGNIDBG": [
            "1",
            "86"
          ]
        }
      ],
      "GELNDPJNLJM": 1,
      "IAHNDJDBCAJ": "\u307B\u3001\u307B\u3093\u3068\u304B\u306D\uFF01\uFF1F"
    },
    {
      "BBPHAPFBFHK": 45,
      "IIBAJDOLFBM": [
        {
          "BNFLNMGOJCM": 30,
          "BPODDGNIDBG": [
            "8",
            "5\r"
          ]
        },
        {
          "BNFLNMGOJCM": 44,
          "BPODDGNIDBG": [
            "8",
            "291"
          ]
        }
      ],
      "GELNDPJNLJM": 8,
      "IAHNDJDBCAJ": "\u3048\u3048\uFF01\u55A7\u5629\u306E\u4EF2\u76F4\u308A\u306A\u3089\r\n\u3053\u306E\u3042\u305F\u3057\u306B\u30C9\u30FC\u30F3\u3068\u4EFB\u305B\u3068\u304D\u306A\u3055\u3044\uFF01"
    },
    {
      "BBPHAPFBFHK": 46,
      "IIBAJDOLFBM": [
        {
          "BNFLNMGOJCM": 45,
          "BPODDGNIDBG": [
            "400"
          ]
        },
        {
          "BNFLNMGOJCM": 26,
          "BPODDGNIDBG": [
            "1200"
          ]
        },
        {
          "BNFLNMGOJCM": 46,
          "BPODDGNIDBG": [

          ]
        }
      ],
      "GELNDPJNLJM": 0,
      "IAHNDJDBCAJ": ""
    }
  ]
}
