{
  "HLBFAIIOKBI": [
    {
      "BBPHAPFBFHK": 1,
      "GJEJFAJHBME": 1,
      "KAOBJENOMHF": 1,
      "DALJDMJEJGE": 4,
      "JJPIKBCKLGF": 200,
      "ENPKFDIPGPF": 200,
      "CFLMCGOJJJD": 2,
      "DLJEENDFNDB": [
        1,
        1,
        1
      ],
      "OFMGALJGDAO": 1,
      "MPIHPCJAHGA": 1,
      "GBJKMHDILHH": 1
    },
    {
      "BBPHAPFBFHK": 2,
      "GJEJFAJHBME": 2,
      "KAOBJENOMHF": 2,
      "DALJDMJEJGE": 3,
      "JJPIKBCKLGF": 210,
      "ENPKFDIPGPF": 200,
      "CFLMCGOJJJD": 2,
      "DLJEENDFNDB": [
        1,
        1,
        1
      ],
      "OFMGALJGDAO": 1,
      "MPIHPCJAHGA": 2,
      "GBJKMHDILHH": 1
    },
    {
      "BBPHAPFBFHK": 3,
      "GJEJFAJHBME": 3,
      "KAOBJENOMHF": 3,
      "DALJDMJEJGE": 2,
      "JJPIKBCKLGF": 215,
      "ENPKFDIPGPF": 195,
      "CFLMCGOJJJD": 2,
      "DLJEENDFNDB": [
        1,
        1,
        1
      ],
      "OFMGALJGDAO": 110,
      "MPIHPCJAHGA": 3,
      "GBJKMHDILHH": 110
    },
    {
      "BBPHAPFBFHK": 4,
      "GJEJFAJHBME": 4,
      "KAOBJENOMHF": 4,
      "DALJDMJEJGE": 1,
      "JJPIKBCKLGF": 200,
      "ENPKFDIPGPF": 210,
      "CFLMCGOJJJD": 2,
      "DLJEENDFNDB": [
        1,
        1,
        1
      ],
      "OFMGALJGDAO": 20,
      "MPIHPCJAHGA": 4,
      "GBJKMHDILHH": 20
    },
    {
      "BBPHAPFBFHK": 5,
      "GJEJFAJHBME": 1,
      "KAOBJENOMHF": 5,
      "DALJDMJEJGE": 8,
      "JJPIKBCKLGF": 195,
      "ENPKFDIPGPF": 215,
      "CFLMCGOJJJD": 2,
      "DLJEENDFNDB": [
        1,
        1,
        1
      ],
      "OFMGALJGDAO": 1050,
      "MPIHPCJAHGA": 5,
      "GBJKMHDILHH": 1050
    },
    {
      "BBPHAPFBFHK": 6,
      "GJEJFAJHBME": 4,
      "KAOBJENOMHF": 6,
      "DALJDMJEJGE": 27,
      "JJPIKBCKLGF": 215,
      "ENPKFDIPGPF": 200,
      "CFLMCGOJJJD": 2,
      "DLJEENDFNDB": [
        1,
        1,
        1
      ],
      "OFMGALJGDAO": 3060,
      "MPIHPCJAHGA": 6,
      "GBJKMHDILHH": 3060
    },
    {
      "BBPHAPFBFHK": 7,
      "GJEJFAJHBME": 4,
      "KAOBJENOMHF": 7,
      "DALJDMJEJGE": 14,
      "JJPIKBCKLGF": 205,
      "ENPKFDIPGPF": 205,
      "CFLMCGOJJJD": 2,
      "DLJEENDFNDB": [
        1,
        1,
        1
      ],
      "OFMGALJGDAO": 1,
      "MPIHPCJAHGA": 7,
      "GBJKMHDILHH": 1
    },
    {
      "BBPHAPFBFHK": 8,
      "GJEJFAJHBME": 1,
      "KAOBJENOMHF": 8,
      "DALJDMJEJGE": 6,
      "JJPIKBCKLGF": 220,
      "ENPKFDIPGPF": 190,
      "CFLMCGOJJJD": 2,
      "DLJEENDFNDB": [
        1,
        1,
        1
      ],
      "OFMGALJGDAO": 20,
      "MPIHPCJAHGA": 8,
      "GBJKMHDILHH": 20
    },
    {
      "BBPHAPFBFHK": 9,
      "GJEJFAJHBME": 1,
      "KAOBJENOMHF": 9,
      "DALJDMJEJGE": 5,
      "JJPIKBCKLGF": 190,
      "ENPKFDIPGPF": 220,
      "CFLMCGOJJJD": 2,
      "DLJEENDFNDB": [
        1,
        1,
        1
      ],
      "OFMGALJGDAO": 70,
      "MPIHPCJAHGA": 9,
      "GBJKMHDILHH": 70
    },
    {
      "BBPHAPFBFHK": 10,
      "GJEJFAJHBME": 1,
      "KAOBJENOMHF": 10,
      "DALJDMJEJGE": 4,
      "JJPIKBCKLGF": 190,
      "ENPKFDIPGPF": 220,
      "CFLMCGOJJJD": 0,
      "DLJEENDFNDB": [
        1,
        1,
        1
      ],
      "OFMGALJGDAO": 0,
      "MPIHPCJAHGA": 10,
      "GBJKMHDILHH": 0
    },
    {
      "BBPHAPFBFHK": 11,
      "GJEJFAJHBME": 2,
      "KAOBJENOMHF": 11,
      "DALJDMJEJGE": 11,
      "JJPIKBCKLGF": 215,
      "ENPKFDIPGPF": 200,
      "CFLMCGOJJJD": 2,
      "DLJEENDFNDB": [
        1,
        1,
        1
      ],
      "OFMGALJGDAO": 350,
      "MPIHPCJAHGA": 11,
      "GBJKMHDILHH": 350
    },
    {
      "BBPHAPFBFHK": 12,
      "GJEJFAJHBME": 1,
      "KAOBJENOMHF": 12,
      "DALJDMJEJGE": 7,
      "JJPIKBCKLGF": 220,
      "ENPKFDIPGPF": 190,
      "CFLMCGOJJJD": 2,
      "DLJEENDFNDB": [
        1,
        1,
        1
      ],
      "OFMGALJGDAO": 190,
      "MPIHPCJAHGA": 12,
      "GBJKMHDILHH": 190
    },
    {
      "BBPHAPFBFHK": 13,
      "GJEJFAJHBME": 2,
      "KAOBJENOMHF": 13,
      "DALJDMJEJGE": 15,
      "JJPIKBCKLGF": 215,
      "ENPKFDIPGPF": 200,
      "CFLMCGOJJJD": 2,
      "DLJEENDFNDB": [
        1,
        1,
        1
      ],
      "OFMGALJGDAO": 270,
      "MPIHPCJAHGA": 13,
      "GBJKMHDILHH": 270
    },
    {
      "BBPHAPFBFHK": 14,
      "GJEJFAJHBME": 1,
      "KAOBJENOMHF": 14,
      "DALJDMJEJGE": 18,
      "JJPIKBCKLGF": 200,
      "ENPKFDIPGPF": 210,
      "CFLMCGOJJJD": 2,
      "DLJEENDFNDB": [
        1,
        1,
        1
      ],
      "OFMGALJGDAO": 645,
      "MPIHPCJAHGA": 14,
      "GBJKMHDILHH": 645
    },
    {
      "BBPHAPFBFHK": 15,
      "GJEJFAJHBME": 1,
      "KAOBJENOMHF": 15,
      "DALJDMJEJGE": 20,
      "JJPIKBCKLGF": 205,
      "ENPKFDIPGPF": 205,
      "CFLMCGOJJJD": 2,
      "DLJEENDFNDB": [
        1,
        1,
        1
      ],
      "OFMGALJGDAO": 840,
      "MPIHPCJAHGA": 15,
      "GBJKMHDILHH": 840
    },
    {
      "BBPHAPFBFHK": 16,
      "GJEJFAJHBME": 2,
      "KAOBJENOMHF": 16,
      "DALJDMJEJGE": 9,
      "JJPIKBCKLGF": 195,
      "ENPKFDIPGPF": 215,
      "CFLMCGOJJJD": 0,
      "DLJEENDFNDB": [
        1,
        1,
        1
      ],
      "OFMGALJGDAO": 0,
      "MPIHPCJAHGA": 16,
      "GBJKMHDILHH": 0
    },
    {
      "BBPHAPFBFHK": 17,
      "GJEJFAJHBME": 2,
      "KAOBJENOMHF": 17,
      "DALJDMJEJGE": 21,
      "JJPIKBCKLGF": 195,
      "ENPKFDIPGPF": 215,
      "CFLMCGOJJJD": 2,
      "DLJEENDFNDB": [
        1,
        1,
        1
      ],
      "OFMGALJGDAO": 750,
      "MPIHPCJAHGA": 17,
      "GBJKMHDILHH": 750
    },
    {
      "BBPHAPFBFHK": 18,
      "GJEJFAJHBME": 2,
      "KAOBJENOMHF": 18,
      "DALJDMJEJGE": 10,
      "JJPIKBCKLGF": 210,
      "ENPKFDIPGPF": 200,
      "CFLMCGOJJJD": 2,
      "DLJEENDFNDB": [
        1,
        1,
        1
      ],
      "OFMGALJGDAO": 550,
      "MPIHPCJAHGA": 18,
      "GBJKMHDILHH": 550
    },
    {
      "BBPHAPFBFHK": 19,
      "GJEJFAJHBME": 1,
      "KAOBJENOMHF": 19,
      "DALJDMJEJGE": 19,
      "JJPIKBCKLGF": 210,
      "ENPKFDIPGPF": 200,
      "CFLMCGOJJJD": 2,
      "DLJEENDFNDB": [
        1,
        1,
        1
      ],
      "OFMGALJGDAO": 1250,
      "MPIHPCJAHGA": 19,
      "GBJKMHDILHH": 1250
    },
    {
      "BBPHAPFBFHK": 20,
      "GJEJFAJHBME": 2,
      "KAOBJENOMHF": 16,
      "DALJDMJEJGE": 9,
      "JJPIKBCKLGF": 195,
      "ENPKFDIPGPF": 215,
      "CFLMCGOJJJD": 2,
      "DLJEENDFNDB": [
        1,
        1,
        1
      ],
      "OFMGALJGDAO": 120,
      "MPIHPCJAHGA": 20,
      "GBJKMHDILHH": 120
    },
    {
      "BBPHAPFBFHK": 21,
      "GJEJFAJHBME": 3,
      "KAOBJENOMHF": 21,
      "DALJDMJEJGE": 16,
      "JJPIKBCKLGF": 200,
      "ENPKFDIPGPF": 220,
      "CFLMCGOJJJD": 2,
      "DLJEENDFNDB": [
        1,
        1,
        1
      ],
      "OFMGALJGDAO": 460,
      "MPIHPCJAHGA": 21,
      "GBJKMHDILHH": 460
    },
    {
      "BBPHAPFBFHK": 22,
      "GJEJFAJHBME": 4,
      "KAOBJENOMHF": 22,
      "DALJDMJEJGE": 17,
      "JJPIKBCKLGF": 205,
      "ENPKFDIPGPF": 205,
      "CFLMCGOJJJD": 2,
      "DLJEENDFNDB": [
        1,
        1,
        1
      ],
      "OFMGALJGDAO": 450,
      "MPIHPCJAHGA": 22,
      "GBJKMHDILHH": 450
    },
    {
      "BBPHAPFBFHK": 23,
      "GJEJFAJHBME": 1,
      "KAOBJENOMHF": 23,
      "DALJDMJEJGE": 4,
      "JJPIKBCKLGF": 200,
      "ENPKFDIPGPF": 200,
      "CFLMCGOJJJD": 1,
      "DLJEENDFNDB": [
        1,
        1,
        1
      ],
      "OFMGALJGDAO": 0,
      "MPIHPCJAHGA": 23,
      "GBJKMHDILHH": 0
    },
    {
      "BBPHAPFBFHK": 24,
      "GJEJFAJHBME": 3,
      "KAOBJENOMHF": 24,
      "DALJDMJEJGE": 12,
      "JJPIKBCKLGF": 210,
      "ENPKFDIPGPF": 200,
      "CFLMCGOJJJD": 2,
      "DLJEENDFNDB": [
        1,
        1,
        1
      ],
      "OFMGALJGDAO": 940,
      "MPIHPCJAHGA": 24,
      "GBJKMHDILHH": 940
    },
    {
      "BBPHAPFBFHK": 25,
      "GJEJFAJHBME": 2,
      "KAOBJENOMHF": 25,
      "DALJDMJEJGE": 1,
      "JJPIKBCKLGF": 200,
      "ENPKFDIPGPF": 200,
      "CFLMCGOJJJD": 1,
      "DLJEENDFNDB": [
        1,
        1,
        1
      ],
      "OFMGALJGDAO": 0,
      "MPIHPCJAHGA": 25,
      "GBJKMHDILHH": 0
    },
    {
      "BBPHAPFBFHK": 26,
      "GJEJFAJHBME": 2,
      "KAOBJENOMHF": 26,
      "DALJDMJEJGE": 22,
      "JJPIKBCKLGF": 190,
      "ENPKFDIPGPF": 190,
      "CFLMCGOJJJD": 2,
      "DLJEENDFNDB": [
        1,
        1,
        1
      ],
      "OFMGALJGDAO": 1,
      "MPIHPCJAHGA": 26,
      "GBJKMHDILHH": 1
    },
    {
      "BBPHAPFBFHK": 27,
      "GJEJFAJHBME": 2,
      "KAOBJENOMHF": 27,
      "DALJDMJEJGE": 3,
      "JJPIKBCKLGF": 200,
      "ENPKFDIPGPF": 210,
      "CFLMCGOJJJD": 2,
      "DLJEENDFNDB": [
        1,
        1,
        1
      ],
      "OFMGALJGDAO": 1170,
      "MPIHPCJAHGA": 27,
      "GBJKMHDILHH": 1170
    },
    {
      "BBPHAPFBFHK": 28,
      "GJEJFAJHBME": 2,
      "KAOBJENOMHF": 28,
      "DALJDMJEJGE": 15,
      "JJPIKBCKLGF": 220,
      "ENPKFDIPGPF": 195,
      "CFLMCGOJJJD": 2,
      "DLJEENDFNDB": [
        1,
        1,
        1
      ],
      "OFMGALJGDAO": 1370,
      "MPIHPCJAHGA": 28,
      "GBJKMHDILHH": 1370
    },
    {
      "BBPHAPFBFHK": 29,
      "GJEJFAJHBME": 1,
      "KAOBJENOMHF": 29,
      "DALJDMJEJGE": 4,
      "JJPIKBCKLGF": 200,
      "ENPKFDIPGPF": 210,
      "CFLMCGOJJJD": 2,
      "DLJEENDFNDB": [
        1,
        1,
        1
      ],
      "OFMGALJGDAO": 1500,
      "MPIHPCJAHGA": 29,
      "GBJKMHDILHH": 1500
    },
    {
      "BBPHAPFBFHK": 30,
      "GJEJFAJHBME": 1,
      "KAOBJENOMHF": 30,
      "DALJDMJEJGE": 25,
      "JJPIKBCKLGF": 210,
      "ENPKFDIPGPF": 200,
      "CFLMCGOJJJD": 2,
      "DLJEENDFNDB": [
        1,
        1,
        1
      ],
      "OFMGALJGDAO": 1620,
      "MPIHPCJAHGA": 30,
      "GBJKMHDILHH": 1620
    },
    {
      "BBPHAPFBFHK": 31,
      "GJEJFAJHBME": 5,
      "KAOBJENOMHF": 31,
      "DALJDMJEJGE": 23,
      "JJPIKBCKLGF": 210,
      "ENPKFDIPGPF": 210,
      "CFLMCGOJJJD": 2,
      "DLJEENDFNDB": [
        1,
        1,
        1
      ],
      "OFMGALJGDAO": 1740,
      "MPIHPCJAHGA": 31,
      "GBJKMHDILHH": 1740
    },
    {
      "BBPHAPFBFHK": 32,
      "GJEJFAJHBME": 5,
      "KAOBJENOMHF": 32,
      "DALJDMJEJGE": 24,
      "JJPIKBCKLGF": 210,
      "ENPKFDIPGPF": 205,
      "CFLMCGOJJJD": 2,
      "DLJEENDFNDB": [
        1,
        1,
        1
      ],
      "OFMGALJGDAO": 1740,
      "MPIHPCJAHGA": 32,
      "GBJKMHDILHH": 1740
    },
    {
      "BBPHAPFBFHK": 33,
      "GJEJFAJHBME": 3,
      "KAOBJENOMHF": 33,
      "DALJDMJEJGE": 2,
      "JJPIKBCKLGF": 215,
      "ENPKFDIPGPF": 205,
      "CFLMCGOJJJD": 2,
      "DLJEENDFNDB": [
        1,
        1,
        1
      ],
      "OFMGALJGDAO": 1870,
      "MPIHPCJAHGA": 33,
      "GBJKMHDILHH": 1870
    },
    {
      "BBPHAPFBFHK": 34,
      "GJEJFAJHBME": 1,
      "KAOBJENOMHF": 34,
      "DALJDMJEJGE": 20,
      "JJPIKBCKLGF": 205,
      "ENPKFDIPGPF": 210,
      "CFLMCGOJJJD": 2,
      "DLJEENDFNDB": [
        1,
        1,
        1
      ],
      "OFMGALJGDAO": 1970,
      "MPIHPCJAHGA": 34,
      "GBJKMHDILHH": 1970
    },
    {
      "BBPHAPFBFHK": 35,
      "GJEJFAJHBME": 1,
      "KAOBJENOMHF": 35,
      "DALJDMJEJGE": 5,
      "JJPIKBCKLGF": 190,
      "ENPKFDIPGPF": 220,
      "CFLMCGOJJJD": 2,
      "DLJEENDFNDB": [
        1,
        1,
        1
      ],
      "OFMGALJGDAO": 2090,
      "MPIHPCJAHGA": 35,
      "GBJKMHDILHH": 2090
    },
    {
      "BBPHAPFBFHK": 36,
      "GJEJFAJHBME": 1,
      "KAOBJENOMHF": 36,
      "DALJDMJEJGE": 26,
      "JJPIKBCKLGF": 200,
      "ENPKFDIPGPF": 200,
      "CFLMCGOJJJD": 1,
      "DLJEENDFNDB": [
        1,
        1,
        1
      ],
      "OFMGALJGDAO": 0,
      "MPIHPCJAHGA": 36,
      "GBJKMHDILHH": 0
    },
    {
      "BBPHAPFBFHK": 37,
      "GJEJFAJHBME": 2,
      "KAOBJENOMHF": 37,
      "DALJDMJEJGE": 9,
      "JJPIKBCKLGF": 200,
      "ENPKFDIPGPF": 215,
      "CFLMCGOJJJD": 2,
      "DLJEENDFNDB": [
        1,
        1,
        1
      ],
      "OFMGALJGDAO": 2240,
      "MPIHPCJAHGA": 37,
      "GBJKMHDILHH": 2240
    },
    {
      "BBPHAPFBFHK": 38,
      "GJEJFAJHBME": 2,
      "KAOBJENOMHF": 38,
      "DALJDMJEJGE": 3,
      "JJPIKBCKLGF": 215,
      "ENPKFDIPGPF": 200,
      "CFLMCGOJJJD": 2,
      "DLJEENDFNDB": [
        1,
        1,
        1
      ],
      "OFMGALJGDAO": 2410,
      "MPIHPCJAHGA": 38,
      "GBJKMHDILHH": 2410
    },
    {
      "BBPHAPFBFHK": 39,
      "GJEJFAJHBME": 1,
      "KAOBJENOMHF": 39,
      "DALJDMJEJGE": 18,
      "JJPIKBCKLGF": 205,
      "ENPKFDIPGPF": 210,
      "CFLMCGOJJJD": 2,
      "DLJEENDFNDB": [
        1,
        1,
        1
      ],
      "OFMGALJGDAO": 2550,
      "MPIHPCJAHGA": 39,
      "GBJKMHDILHH": 2550
    },
    {
      "BBPHAPFBFHK": 40,
      "GJEJFAJHBME": 4,
      "KAOBJENOMHF": 40,
      "DALJDMJEJGE": 1,
      "JJPIKBCKLGF": 220,
      "ENPKFDIPGPF": 200,
      "CFLMCGOJJJD": 2,
      "DLJEENDFNDB": [
        1,
        1,
        1
      ],
      "OFMGALJGDAO": 2250,
      "MPIHPCJAHGA": 40,
      "GBJKMHDILHH": 2250
    },
    {
      "BBPHAPFBFHK": 41,
      "GJEJFAJHBME": 1,
      "KAOBJENOMHF": 41,
      "DALJDMJEJGE": 4,
      "JJPIKBCKLGF": 210,
      "ENPKFDIPGPF": 205,
      "CFLMCGOJJJD": 2,
      "DLJEENDFNDB": [
        1,
        1,
        1
      ],
      "OFMGALJGDAO": 2720,
      "MPIHPCJAHGA": 41,
      "GBJKMHDILHH": 2720
    },
    {
      "BBPHAPFBFHK": 42,
      "GJEJFAJHBME": 2,
      "KAOBJENOMHF": 42,
      "DALJDMJEJGE": 10,
      "JJPIKBCKLGF": 215,
      "ENPKFDIPGPF": 200,
      "CFLMCGOJJJD": 2,
      "DLJEENDFNDB": [
        1,
        1,
        1
      ],
      "OFMGALJGDAO": 2890,
      "MPIHPCJAHGA": 42,
      "GBJKMHDILHH": 2890
    },
    {
      "BBPHAPFBFHK": 43,
      "GJEJFAJHBME": 1,
      "KAOBJENOMHF": 43,
      "DALJDMJEJGE": 4,
      "JJPIKBCKLGF": 205,
      "ENPKFDIPGPF": 210,
      "CFLMCGOJJJD": 2,
      "DLJEENDFNDB": [
        1,
        1,
        1
      ],
      "OFMGALJGDAO": 3050,
      "MPIHPCJAHGA": 43,
      "GBJKMHDILHH": 3050
    },
    {
      "BBPHAPFBFHK": 44,
      "GJEJFAJHBME": 1,
      "KAOBJENOMHF": 44,
      "DALJDMJEJGE": 6,
      "JJPIKBCKLGF": 200,
      "ENPKFDIPGPF": 215,
      "CFLMCGOJJJD": 2,
      "DLJEENDFNDB": [
        1,
        1,
        1
      ],
      "OFMGALJGDAO": 3200,
      "MPIHPCJAHGA": 44,
      "GBJKMHDILHH": 3200
    },
    {
      "BBPHAPFBFHK": 45,
      "GJEJFAJHBME": 2,
      "KAOBJENOMHF": 45,
      "DALJDMJEJGE": 3,
      "JJPIKBCKLGF": 225,
      "ENPKFDIPGPF": 190,
      "CFLMCGOJJJD": 2,
      "DLJEENDFNDB": [
        1,
        1,
        1
      ],
      "OFMGALJGDAO": 3330,
      "MPIHPCJAHGA": 45,
      "GBJKMHDILHH": 3330
    },
    {
      "BBPHAPFBFHK": 46,
      "GJEJFAJHBME": 5,
      "KAOBJENOMHF": 46,
      "DALJDMJEJGE": 23,
      "JJPIKBCKLGF": 200,
      "ENPKFDIPGPF": 205,
      "CFLMCGOJJJD": 2,
      "DLJEENDFNDB": [
        1,
        1,
        1
      ],
      "OFMGALJGDAO": 2930,
      "MPIHPCJAHGA": 46,
      "GBJKMHDILHH": 2930
    },
    {
      "BBPHAPFBFHK": 47,
      "GJEJFAJHBME": 1,
      "KAOBJENOMHF": 47,
      "DALJDMJEJGE": 5,
      "JJPIKBCKLGF": 195,
      "ENPKFDIPGPF": 220,
      "CFLMCGOJJJD": 2,
      "DLJEENDFNDB": [
        1,
        1,
        1
      ],
      "OFMGALJGDAO": 3460,
      "MPIHPCJAHGA": 47,
      "GBJKMHDILHH": 3460
    },
    {
      "BBPHAPFBFHK": 48,
      "GJEJFAJHBME": 1,
      "KAOBJENOMHF": 48,
      "DALJDMJEJGE": 7,
      "JJPIKBCKLGF": 220,
      "ENPKFDIPGPF": 195,
      "CFLMCGOJJJD": 2,
      "DLJEENDFNDB": [
        1,
        1,
        1
      ],
      "OFMGALJGDAO": 3610,
      "MPIHPCJAHGA": 48,
      "GBJKMHDILHH": 3610
    },
    {
      "BBPHAPFBFHK": 49,
      "GJEJFAJHBME": 2,
      "KAOBJENOMHF": 49,
      "DALJDMJEJGE": 9,
      "JJPIKBCKLGF": 210,
      "ENPKFDIPGPF": 205,
      "CFLMCGOJJJD": 2,
      "DLJEENDFNDB": [
        1,
        1,
        1
      ],
      "OFMGALJGDAO": 3770,
      "MPIHPCJAHGA": 49,
      "GBJKMHDILHH": 3770
    },
    {
      "BBPHAPFBFHK": 50,
      "GJEJFAJHBME": 1,
      "KAOBJENOMHF": 50,
      "DALJDMJEJGE": 8,
      "JJPIKBCKLGF": 200,
      "ENPKFDIPGPF": 215,
      "CFLMCGOJJJD": 2,
      "DLJEENDFNDB": [
        1,
        1,
        1
      ],
      "OFMGALJGDAO": 3960,
      "MPIHPCJAHGA": 50,
      "GBJKMHDILHH": 3960
    },
    {
      "BBPHAPFBFHK": 51,
      "GJEJFAJHBME": 5,
      "KAOBJENOMHF": 51,
      "DALJDMJEJGE": 28,
      "JJPIKBCKLGF": 215,
      "ENPKFDIPGPF": 205,
      "CFLMCGOJJJD": 2,
      "DLJEENDFNDB": [
        1,
        1,
        1
      ],
      "OFMGALJGDAO": 4070,
      "MPIHPCJAHGA": 51,
      "GBJKMHDILHH": 4070
    },
    {
      "BBPHAPFBFHK": 52,
      "GJEJFAJHBME": 1,
      "KAOBJENOMHF": 52,
      "DALJDMJEJGE": 4,
      "JJPIKBCKLGF": 200,
      "ENPKFDIPGPF": 215,
      "CFLMCGOJJJD": 2,
      "DLJEENDFNDB": [
        1,
        1,
        1
      ],
      "OFMGALJGDAO": 4240,
      "MPIHPCJAHGA": 52,
      "GBJKMHDILHH": 4240
    },
    {
      "BBPHAPFBFHK": 53,
      "GJEJFAJHBME": 4,
      "KAOBJENOMHF": 53,
      "DALJDMJEJGE": 29,
      "JJPIKBCKLGF": 215,
      "ENPKFDIPGPF": 200,
      "CFLMCGOJJJD": 2,
      "DLJEENDFNDB": [
        1,
        1,
        1
      ],
      "OFMGALJGDAO": 4360,
      "MPIHPCJAHGA": 53,
      "GBJKMHDILHH": 4360
    },
    {
      "BBPHAPFBFHK": 54,
      "GJEJFAJHBME": 3,
      "KAOBJENOMHF": 54,
      "DALJDMJEJGE": 16,
      "JJPIKBCKLGF": 205,
      "ENPKFDIPGPF": 210,
      "CFLMCGOJJJD": 2,
      "DLJEENDFNDB": [
        1,
        1,
        1
      ],
      "OFMGALJGDAO": 4540,
      "MPIHPCJAHGA": 54,
      "GBJKMHDILHH": 4540
    },
    {
      "BBPHAPFBFHK": 55,
      "GJEJFAJHBME": 2,
      "KAOBJENOMHF": 55,
      "DALJDMJEJGE": 30,
      "JJPIKBCKLGF": 215,
      "ENPKFDIPGPF": 205,
      "CFLMCGOJJJD": 2,
      "DLJEENDFNDB": [
        1,
        1,
        1
      ],
      "OFMGALJGDAO": 4710,
      "MPIHPCJAHGA": 55,
      "GBJKMHDILHH": 4710
    },
    {
      "BBPHAPFBFHK": 56,
      "GJEJFAJHBME": 1,
      "KAOBJENOMHF": 56,
      "DALJDMJEJGE": 6,
      "JJPIKBCKLGF": 215,
      "ENPKFDIPGPF": 205,
      "CFLMCGOJJJD": 2,
      "DLJEENDFNDB": [
        1,
        1,
        1
      ],
      "OFMGALJGDAO": 4890,
      "MPIHPCJAHGA": 56,
      "GBJKMHDILHH": 4890
    },
    {
      "BBPHAPFBFHK": 57,
      "GJEJFAJHBME": 2,
      "KAOBJENOMHF": 57,
      "DALJDMJEJGE": 31,
      "JJPIKBCKLGF": 220,
      "ENPKFDIPGPF": 190,
      "CFLMCGOJJJD": 2,
      "DLJEENDFNDB": [
        1,
        1,
        1
      ],
      "OFMGALJGDAO": 5060,
      "MPIHPCJAHGA": 57,
      "GBJKMHDILHH": 5060
    },
    {
      "BBPHAPFBFHK": 58,
      "GJEJFAJHBME": 4,
      "KAOBJENOMHF": 58,
      "DALJDMJEJGE": 32,
      "JJPIKBCKLGF": 220,
      "ENPKFDIPGPF": 190,
      "CFLMCGOJJJD": 2,
      "DLJEENDFNDB": [
        1,
        1,
        1
      ],
      "OFMGALJGDAO": 5220,
      "MPIHPCJAHGA": 58,
      "GBJKMHDILHH": 5220
    },
    {
      "BBPHAPFBFHK": 59,
      "GJEJFAJHBME": 3,
      "KAOBJENOMHF": 59,
      "DALJDMJEJGE": 33,
      "JJPIKBCKLGF": 210,
      "ENPKFDIPGPF": 210,
      "CFLMCGOJJJD": 2,
      "DLJEENDFNDB": [
        1,
        1,
        1
      ],
      "OFMGALJGDAO": 5350,
      "MPIHPCJAHGA": 59,
      "GBJKMHDILHH": 5350
    },
    {
      "BBPHAPFBFHK": 60,
      "GJEJFAJHBME": 2,
      "KAOBJENOMHF": 60,
      "DALJDMJEJGE": 10,
      "JJPIKBCKLGF": 220,
      "ENPKFDIPGPF": 190,
      "CFLMCGOJJJD": 2,
      "DLJEENDFNDB": [
        1,
        1,
        1
      ],
      "OFMGALJGDAO": 5470,
      "MPIHPCJAHGA": 60,
      "GBJKMHDILHH": 5470
    },
    {
      "BBPHAPFBFHK": 61,
      "GJEJFAJHBME": 3,
      "KAOBJENOMHF": 61,
      "DALJDMJEJGE": 34,
      "JJPIKBCKLGF": 205,
      "ENPKFDIPGPF": 215,
      "CFLMCGOJJJD": 2,
      "DLJEENDFNDB": [
        1,
        1,
        1
      ],
      "OFMGALJGDAO": 5610,
      "MPIHPCJAHGA": 61,
      "GBJKMHDILHH": 5610
    },
    {
      "BBPHAPFBFHK": 62,
      "GJEJFAJHBME": 2,
      "KAOBJENOMHF": 62,
      "DALJDMJEJGE": 21,
      "JJPIKBCKLGF": 200,
      "ENPKFDIPGPF": 220,
      "CFLMCGOJJJD": 2,
      "DLJEENDFNDB": [
        1,
        1,
        1
      ],
      "OFMGALJGDAO": 5740,
      "MPIHPCJAHGA": 62,
      "GBJKMHDILHH": 5740
    },
    {
      "BBPHAPFBFHK": 63,
      "GJEJFAJHBME": 1,
      "KAOBJENOMHF": 63,
      "DALJDMJEJGE": 35,
      "JJPIKBCKLGF": 205,
      "ENPKFDIPGPF": 205,
      "CFLMCGOJJJD": 2,
      "DLJEENDFNDB": [
        1,
        1,
        1
      ],
      "OFMGALJGDAO": 5860,
      "MPIHPCJAHGA": 63,
      "GBJKMHDILHH": 5860
    },
    {
      "BBPHAPFBFHK": 64,
      "GJEJFAJHBME": 4,
      "KAOBJENOMHF": 64,
      "DALJDMJEJGE": 14,
      "JJPIKBCKLGF": 210,
      "ENPKFDIPGPF": 210,
      "CFLMCGOJJJD": 2,
      "DLJEENDFNDB": [
        1,
        1,
        1
      ],
      "OFMGALJGDAO": 5990,
      "MPIHPCJAHGA": 64,
      "GBJKMHDILHH": 5990
    },
    {
      "BBPHAPFBFHK": 65,
      "GJEJFAJHBME": 1,
      "KAOBJENOMHF": 65,
      "DALJDMJEJGE": 7,
      "JJPIKBCKLGF": 220,
      "ENPKFDIPGPF": 195,
      "CFLMCGOJJJD": 2,
      "DLJEENDFNDB": [
        1,
        1,
        1
      ],
      "OFMGALJGDAO": 6710,
      "MPIHPCJAHGA": 65,
      "GBJKMHDILHH": 6710
    },
    {
      "BBPHAPFBFHK": 66,
      "GJEJFAJHBME": 1,
      "KAOBJENOMHF": 66,
      "DALJDMJEJGE": 39,
      "JJPIKBCKLGF": 210,
      "ENPKFDIPGPF": 210,
      "CFLMCGOJJJD": 2,
      "DLJEENDFNDB": [
        1,
        1,
        1
      ],
      "OFMGALJGDAO": 6430,
      "MPIHPCJAHGA": 66,
      "GBJKMHDILHH": 6430
    },
    {
      "BBPHAPFBFHK": 67,
      "GJEJFAJHBME": 1,
      "KAOBJENOMHF": 67,
      "DALJDMJEJGE": 4,
      "JJPIKBCKLGF": 200,
      "ENPKFDIPGPF": 200,
      "CFLMCGOJJJD": 0,
      "DLJEENDFNDB": [
        1,
        1,
        1
      ],
      "OFMGALJGDAO": 0,
      "MPIHPCJAHGA": 1,
      "GBJKMHDILHH": 0
    },
    {
      "BBPHAPFBFHK": 68,
      "GJEJFAJHBME": 1,
      "KAOBJENOMHF": 68,
      "DALJDMJEJGE": 4,
      "JJPIKBCKLGF": 200,
      "ENPKFDIPGPF": 200,
      "CFLMCGOJJJD": 0,
      "DLJEENDFNDB": [
        1,
        1,
        1
      ],
      "OFMGALJGDAO": 0,
      "MPIHPCJAHGA": 1,
      "GBJKMHDILHH": 0
    },
    {
      "BBPHAPFBFHK": 69,
      "GJEJFAJHBME": 1,
      "KAOBJENOMHF": 69,
      "DALJDMJEJGE": 4,
      "JJPIKBCKLGF": 200,
      "ENPKFDIPGPF": 200,
      "CFLMCGOJJJD": 0,
      "DLJEENDFNDB": [
        1,
        1,
        1
      ],
      "OFMGALJGDAO": 0,
      "MPIHPCJAHGA": 1,
      "GBJKMHDILHH": 0
    },
    {
      "BBPHAPFBFHK": 70,
      "GJEJFAJHBME": 1,
      "KAOBJENOMHF": 70,
      "DALJDMJEJGE": 4,
      "JJPIKBCKLGF": 200,
      "ENPKFDIPGPF": 200,
      "CFLMCGOJJJD": 0,
      "DLJEENDFNDB": [
        1,
        1,
        1
      ],
      "OFMGALJGDAO": 0,
      "MPIHPCJAHGA": 1,
      "GBJKMHDILHH": 0
    },
    {
      "BBPHAPFBFHK": 71,
      "GJEJFAJHBME": 1,
      "KAOBJENOMHF": 71,
      "DALJDMJEJGE": 4,
      "JJPIKBCKLGF": 200,
      "ENPKFDIPGPF": 200,
      "CFLMCGOJJJD": 0,
      "DLJEENDFNDB": [
        1,
        1,
        1
      ],
      "OFMGALJGDAO": 0,
      "MPIHPCJAHGA": 1,
      "GBJKMHDILHH": 0
    },
    {
      "BBPHAPFBFHK": 72,
      "GJEJFAJHBME": 1,
      "KAOBJENOMHF": 72,
      "DALJDMJEJGE": 4,
      "JJPIKBCKLGF": 200,
      "ENPKFDIPGPF": 200,
      "CFLMCGOJJJD": 0,
      "DLJEENDFNDB": [
        1,
        1,
        1
      ],
      "OFMGALJGDAO": 0,
      "MPIHPCJAHGA": 1,
      "GBJKMHDILHH": 0
    },
    {
      "BBPHAPFBFHK": 73,
      "GJEJFAJHBME": 1,
      "KAOBJENOMHF": 73,
      "DALJDMJEJGE": 4,
      "JJPIKBCKLGF": 200,
      "ENPKFDIPGPF": 200,
      "CFLMCGOJJJD": 0,
      "DLJEENDFNDB": [
        1,
        1,
        1
      ],
      "OFMGALJGDAO": 0,
      "MPIHPCJAHGA": 1,
      "GBJKMHDILHH": 0
    },
    {
      "BBPHAPFBFHK": 74,
      "GJEJFAJHBME": 1,
      "KAOBJENOMHF": 74,
      "DALJDMJEJGE": 4,
      "JJPIKBCKLGF": 200,
      "ENPKFDIPGPF": 200,
      "CFLMCGOJJJD": 0,
      "DLJEENDFNDB": [
        1,
        1,
        1
      ],
      "OFMGALJGDAO": 0,
      "MPIHPCJAHGA": 1,
      "GBJKMHDILHH": 0
    },
    {
      "BBPHAPFBFHK": 75,
      "GJEJFAJHBME": 1,
      "KAOBJENOMHF": 75,
      "DALJDMJEJGE": 4,
      "JJPIKBCKLGF": 200,
      "ENPKFDIPGPF": 200,
      "CFLMCGOJJJD": 0,
      "DLJEENDFNDB": [
        1,
        1,
        1
      ],
      "OFMGALJGDAO": 0,
      "MPIHPCJAHGA": 1,
      "GBJKMHDILHH": 0
    },
    {
      "BBPHAPFBFHK": 76,
      "GJEJFAJHBME": 1,
      "KAOBJENOMHF": 76,
      "DALJDMJEJGE": 4,
      "JJPIKBCKLGF": 200,
      "ENPKFDIPGPF": 200,
      "CFLMCGOJJJD": 0,
      "DLJEENDFNDB": [
        1,
        1,
        1
      ],
      "OFMGALJGDAO": 0,
      "MPIHPCJAHGA": 1,
      "GBJKMHDILHH": 0
    },
    {
      "BBPHAPFBFHK": 77,
      "GJEJFAJHBME": 1,
      "KAOBJENOMHF": 77,
      "DALJDMJEJGE": 4,
      "JJPIKBCKLGF": 200,
      "ENPKFDIPGPF": 200,
      "CFLMCGOJJJD": 0,
      "DLJEENDFNDB": [
        1,
        1,
        1
      ],
      "OFMGALJGDAO": 0,
      "MPIHPCJAHGA": 1,
      "GBJKMHDILHH": 0
    },
    {
      "BBPHAPFBFHK": 78,
      "GJEJFAJHBME": 1,
      "KAOBJENOMHF": 78,
      "DALJDMJEJGE": 4,
      "JJPIKBCKLGF": 200,
      "ENPKFDIPGPF": 200,
      "CFLMCGOJJJD": 0,
      "DLJEENDFNDB": [
        1,
        1,
        1
      ],
      "OFMGALJGDAO": 0,
      "MPIHPCJAHGA": 1,
      "GBJKMHDILHH": 0
    },
    {
      "BBPHAPFBFHK": 79,
      "GJEJFAJHBME": 1,
      "KAOBJENOMHF": 79,
      "DALJDMJEJGE": 4,
      "JJPIKBCKLGF": 200,
      "ENPKFDIPGPF": 200,
      "CFLMCGOJJJD": 0,
      "DLJEENDFNDB": [
        1,
        1,
        1
      ],
      "OFMGALJGDAO": 0,
      "MPIHPCJAHGA": 1,
      "GBJKMHDILHH": 0
    },
    {
      "BBPHAPFBFHK": 80,
      "GJEJFAJHBME": 1,
      "KAOBJENOMHF": 80,
      "DALJDMJEJGE": 4,
      "JJPIKBCKLGF": 200,
      "ENPKFDIPGPF": 200,
      "CFLMCGOJJJD": 0,
      "DLJEENDFNDB": [
        1,
        1,
        1
      ],
      "OFMGALJGDAO": 0,
      "MPIHPCJAHGA": 1,
      "GBJKMHDILHH": 0
    },
    {
      "BBPHAPFBFHK": 81,
      "GJEJFAJHBME": 1,
      "KAOBJENOMHF": 81,
      "DALJDMJEJGE": 4,
      "JJPIKBCKLGF": 200,
      "ENPKFDIPGPF": 200,
      "CFLMCGOJJJD": 0,
      "DLJEENDFNDB": [
        1,
        1,
        1
      ],
      "OFMGALJGDAO": 0,
      "MPIHPCJAHGA": 1,
      "GBJKMHDILHH": 0
    },
    {
      "BBPHAPFBFHK": 82,
      "GJEJFAJHBME": 1,
      "KAOBJENOMHF": 82,
      "DALJDMJEJGE": 4,
      "JJPIKBCKLGF": 200,
      "ENPKFDIPGPF": 200,
      "CFLMCGOJJJD": 0,
      "DLJEENDFNDB": [
        1,
        1,
        1
      ],
      "OFMGALJGDAO": 0,
      "MPIHPCJAHGA": 1,
      "GBJKMHDILHH": 0
    },
    {
      "BBPHAPFBFHK": 83,
      "GJEJFAJHBME": 1,
      "KAOBJENOMHF": 83,
      "DALJDMJEJGE": 4,
      "JJPIKBCKLGF": 200,
      "ENPKFDIPGPF": 200,
      "CFLMCGOJJJD": 0,
      "DLJEENDFNDB": [
        1,
        1,
        1
      ],
      "OFMGALJGDAO": 0,
      "MPIHPCJAHGA": 1,
      "GBJKMHDILHH": 0
    },
    {
      "BBPHAPFBFHK": 84,
      "GJEJFAJHBME": 1,
      "KAOBJENOMHF": 84,
      "DALJDMJEJGE": 4,
      "JJPIKBCKLGF": 200,
      "ENPKFDIPGPF": 200,
      "CFLMCGOJJJD": 0,
      "DLJEENDFNDB": [
        1,
        1,
        1
      ],
      "OFMGALJGDAO": 0,
      "MPIHPCJAHGA": 1,
      "GBJKMHDILHH": 0
    },
    {
      "BBPHAPFBFHK": 85,
      "GJEJFAJHBME": 1,
      "KAOBJENOMHF": 85,
      "DALJDMJEJGE": 4,
      "JJPIKBCKLGF": 200,
      "ENPKFDIPGPF": 200,
      "CFLMCGOJJJD": 0,
      "DLJEENDFNDB": [
        1,
        1,
        1
      ],
      "OFMGALJGDAO": 0,
      "MPIHPCJAHGA": 1,
      "GBJKMHDILHH": 0
    },
    {
      "BBPHAPFBFHK": 86,
      "GJEJFAJHBME": 1,
      "KAOBJENOMHF": 86,
      "DALJDMJEJGE": 4,
      "JJPIKBCKLGF": 200,
      "ENPKFDIPGPF": 200,
      "CFLMCGOJJJD": 0,
      "DLJEENDFNDB": [
        1,
        1,
        1
      ],
      "OFMGALJGDAO": 0,
      "MPIHPCJAHGA": 1,
      "GBJKMHDILHH": 0
    },
    {
      "BBPHAPFBFHK": 87,
      "GJEJFAJHBME": 1,
      "KAOBJENOMHF": 87,
      "DALJDMJEJGE": 4,
      "JJPIKBCKLGF": 200,
      "ENPKFDIPGPF": 200,
      "CFLMCGOJJJD": 0,
      "DLJEENDFNDB": [
        1,
        1,
        1
      ],
      "OFMGALJGDAO": 0,
      "MPIHPCJAHGA": 1,
      "GBJKMHDILHH": 0
    },
    {
      "BBPHAPFBFHK": 88,
      "GJEJFAJHBME": 1,
      "KAOBJENOMHF": 88,
      "DALJDMJEJGE": 4,
      "JJPIKBCKLGF": 200,
      "ENPKFDIPGPF": 200,
      "CFLMCGOJJJD": 0,
      "DLJEENDFNDB": [
        1,
        1,
        1
      ],
      "OFMGALJGDAO": 0,
      "MPIHPCJAHGA": 1,
      "GBJKMHDILHH": 0
    },
    {
      "BBPHAPFBFHK": 89,
      "GJEJFAJHBME": 1,
      "KAOBJENOMHF": 89,
      "DALJDMJEJGE": 4,
      "JJPIKBCKLGF": 200,
      "ENPKFDIPGPF": 200,
      "CFLMCGOJJJD": 0,
      "DLJEENDFNDB": [
        1,
        1,
        1
      ],
      "OFMGALJGDAO": 0,
      "MPIHPCJAHGA": 1,
      "GBJKMHDILHH": 0
    },
    {
      "BBPHAPFBFHK": 90,
      "GJEJFAJHBME": 1,
      "KAOBJENOMHF": 90,
      "DALJDMJEJGE": 4,
      "JJPIKBCKLGF": 200,
      "ENPKFDIPGPF": 200,
      "CFLMCGOJJJD": 0,
      "DLJEENDFNDB": [
        1,
        1,
        1
      ],
      "OFMGALJGDAO": 0,
      "MPIHPCJAHGA": 1,
      "GBJKMHDILHH": 0
    },
    {
      "BBPHAPFBFHK": 91,
      "GJEJFAJHBME": 1,
      "KAOBJENOMHF": 91,
      "DALJDMJEJGE": 4,
      "JJPIKBCKLGF": 200,
      "ENPKFDIPGPF": 200,
      "CFLMCGOJJJD": 0,
      "DLJEENDFNDB": [
        1,
        1,
        1
      ],
      "OFMGALJGDAO": 0,
      "MPIHPCJAHGA": 1,
      "GBJKMHDILHH": 0
    },
    {
      "BBPHAPFBFHK": 92,
      "GJEJFAJHBME": 1,
      "KAOBJENOMHF": 92,
      "DALJDMJEJGE": 4,
      "JJPIKBCKLGF": 200,
      "ENPKFDIPGPF": 200,
      "CFLMCGOJJJD": 0,
      "DLJEENDFNDB": [
        1,
        1,
        1
      ],
      "OFMGALJGDAO": 0,
      "MPIHPCJAHGA": 1,
      "GBJKMHDILHH": 0
    },
    {
      "BBPHAPFBFHK": 93,
      "GJEJFAJHBME": 1,
      "KAOBJENOMHF": 93,
      "DALJDMJEJGE": 4,
      "JJPIKBCKLGF": 200,
      "ENPKFDIPGPF": 200,
      "CFLMCGOJJJD": 0,
      "DLJEENDFNDB": [
        1,
        1,
        1
      ],
      "OFMGALJGDAO": 0,
      "MPIHPCJAHGA": 1,
      "GBJKMHDILHH": 0
    },
    {
      "BBPHAPFBFHK": 94,
      "GJEJFAJHBME": 1,
      "KAOBJENOMHF": 94,
      "DALJDMJEJGE": 4,
      "JJPIKBCKLGF": 200,
      "ENPKFDIPGPF": 200,
      "CFLMCGOJJJD": 0,
      "DLJEENDFNDB": [
        1,
        1,
        1
      ],
      "OFMGALJGDAO": 0,
      "MPIHPCJAHGA": 1,
      "GBJKMHDILHH": 0
    },
    {
      "BBPHAPFBFHK": 95,
      "GJEJFAJHBME": 1,
      "KAOBJENOMHF": 95,
      "DALJDMJEJGE": 4,
      "JJPIKBCKLGF": 200,
      "ENPKFDIPGPF": 200,
      "CFLMCGOJJJD": 0,
      "DLJEENDFNDB": [
        1,
        1,
        1
      ],
      "OFMGALJGDAO": 0,
      "MPIHPCJAHGA": 1,
      "GBJKMHDILHH": 0
    },
    {
      "BBPHAPFBFHK": 96,
      "GJEJFAJHBME": 1,
      "KAOBJENOMHF": 96,
      "DALJDMJEJGE": 4,
      "JJPIKBCKLGF": 200,
      "ENPKFDIPGPF": 200,
      "CFLMCGOJJJD": 0,
      "DLJEENDFNDB": [
        1,
        1,
        1
      ],
      "OFMGALJGDAO": 0,
      "MPIHPCJAHGA": 1,
      "GBJKMHDILHH": 0
    },
    {
      "BBPHAPFBFHK": 97,
      "GJEJFAJHBME": 1,
      "KAOBJENOMHF": 97,
      "DALJDMJEJGE": 4,
      "JJPIKBCKLGF": 200,
      "ENPKFDIPGPF": 200,
      "CFLMCGOJJJD": 0,
      "DLJEENDFNDB": [
        1,
        1,
        1
      ],
      "OFMGALJGDAO": 0,
      "MPIHPCJAHGA": 1,
      "GBJKMHDILHH": 0
    },
    {
      "BBPHAPFBFHK": 98,
      "GJEJFAJHBME": 1,
      "KAOBJENOMHF": 98,
      "DALJDMJEJGE": 4,
      "JJPIKBCKLGF": 200,
      "ENPKFDIPGPF": 200,
      "CFLMCGOJJJD": 0,
      "DLJEENDFNDB": [
        1,
        1,
        1
      ],
      "OFMGALJGDAO": 0,
      "MPIHPCJAHGA": 1,
      "GBJKMHDILHH": 0
    },
    {
      "BBPHAPFBFHK": 99,
      "GJEJFAJHBME": 1,
      "KAOBJENOMHF": 99,
      "DALJDMJEJGE": 4,
      "JJPIKBCKLGF": 200,
      "ENPKFDIPGPF": 200,
      "CFLMCGOJJJD": 0,
      "DLJEENDFNDB": [
        1,
        1,
        1
      ],
      "OFMGALJGDAO": 0,
      "MPIHPCJAHGA": 1,
      "GBJKMHDILHH": 0
    },
    {
      "BBPHAPFBFHK": 100,
      "GJEJFAJHBME": 1,
      "KAOBJENOMHF": 100,
      "DALJDMJEJGE": 4,
      "JJPIKBCKLGF": 200,
      "ENPKFDIPGPF": 200,
      "CFLMCGOJJJD": 0,
      "DLJEENDFNDB": [
        1,
        1,
        1
      ],
      "OFMGALJGDAO": 0,
      "MPIHPCJAHGA": 1,
      "GBJKMHDILHH": 0
    }
  ]
}
